hasr/__init__.py
hasr/_modidx.py
hasr/attr.py
hasr/atyp.py
hasr/call.py
hasr/core.py
hasr/lens.py
hasr-0.0.8.dist-info/LICENSE
hasr-0.0.8.dist-info/METADATA
hasr-0.0.8.dist-info/WHEEL
hasr-0.0.8.dist-info/entry_points.txt
hasr-0.0.8.dist-info/top_level.txt
hasr-0.0.8.dist-info/RECORD
