Metadata-Version: 2.1
Name: hasr
Version: 0.0.8
Summary: hasr
Home-page: https://github.com/dsm-72/hasr
Author: dsm-72
Author-email: sumner.magruder@yale.edu
License: Apache Software License 2.0
Keywords: hasr is question bool type guard typeguard check hasr
Classifier: Development Status :: 4 - Beta
Classifier: Intended Audience :: Developers
Classifier: Natural Language :: English
Classifier: Programming Language :: Python :: 3.11
Classifier: License :: OSI Approved :: Apache Software License
Requires-Python: >=3.11
License-File: LICENSE
Requires-Dist: itry
Requires-Dist: nchr
Requires-Dist: nlit
Requires-Dist: chck
Provides-Extra: dev
